LICENSE
MANIFEST.in
README.rst
requirements.txt
setup.py
test-requirements.txt
tox.ini
schema_res/__init__.py
schema_res/descriptor.py
schema_res/helpers.py
schema_res/loader.py
schema_resource.egg-info/PKG-INFO
schema_resource.egg-info/SOURCES.txt
schema_resource.egg-info/dependency_links.txt
schema_resource.egg-info/requires.txt
schema_resource.egg-info/top_level.txt
tests/__init__.py
tests/unit/__init__.py
tests/unit/test_descriptor.py
tests/unit/test_helpers.py
tests/unit/test_loader.py