Metadata-Version: 1.1
Name: schema-resource
Version: 0.0.1
Summary: Schema Resources
Home-page: https://github.com/klmitch/schema-resource
Author: Kevin L. Mitchell
Author-email: klmitch@mit.edu
License: UNKNOWN
Platform: UNKNOWN
Classifier: Development Status :: 3 - Alpha
Classifier: Intended Audience :: Developers
Classifier: License :: OSI Approved :: Apache Software License
Classifier: Operating System :: OS Independent
Classifier: Programming Language :: Python :: 2.7
Classifier: Programming Language :: Python :: 3.5
Classifier: Programming Language :: Python :: 3.6
Classifier: Programming Language :: Python :: 3.7
